taobaopyx/__init__.py
taobaopyx/taobao.py
taobaopyx-0.1.2.dist-info/METADATA
taobaopyx-0.1.2.dist-info/WHEEL
taobaopyx-0.1.2.dist-info/top_level.txt
taobaopyx-0.1.2.dist-info/RECORD
