Metadata-Version: 2.4
Name: taobaopyx
Version: 0.1.2
Summary: Add your description here
Requires-Python: >=3.12
Requires-Dist: httpx
